nonebot_plugin_sunset_reminder/__init__.py
nonebot_plugin_sunset_reminder/commands.py
nonebot_plugin_sunset_reminder/config.py
nonebot_plugin_sunset_reminder/data.py
nonebot_plugin_sunset_reminder/db_action.py
nonebot_plugin_sunset_reminder/reminder.py
nonebot_plugin_sunset_reminder-0.1.0.dist-info/licenses/LICENSE
nonebot_plugin_sunset_reminder-0.1.0.dist-info/METADATA
nonebot_plugin_sunset_reminder-0.1.0.dist-info/WHEEL
nonebot_plugin_sunset_reminder-0.1.0.dist-info/top_level.txt
nonebot_plugin_sunset_reminder-0.1.0.dist-info/RECORD
