Metadata-Version: 2.4
Name: nonebot-plugin-sunset-reminder
Version: 0.1.0
Summary: a plugin to inform flame cloud infos.
Author-email: HTony03 <HTony03@foxmail.com>
Project-URL: Repository, https://github.com/HTony03/nonebot-plugin-sunset-reminder
Requires-Python: <3.13,>=3.10
License-File: LICENSE
Requires-Dist: nonebot2<3.0.0,>=2.4.2
Requires-Dist: nonebot-plugin-localstore<1.0.0,>=0.7.4
Requires-Dist: nonebot-plugin-apscheduler<1.0.0,>=0.5.0
Requires-Dist: nonebot-adapter-onebot<3.0.0,>=2.4.6
Requires-Dist: aiohttp<4.0.0,~=3.11
Dynamic: license-file
